channelpy/__init__.py
channelpy/base_connection.py
channelpy/chan.py
channelpy/connections.py
channelpy/exceptions.py
channelpy/rabbitpy_connection.py
channelpy-0.2.dist-info/DESCRIPTION.rst
channelpy-0.2.dist-info/METADATA
channelpy-0.2.dist-info/metadata.json
channelpy-0.2.dist-info/RECORD
channelpy-0.2.dist-info/top_level.txt
channelpy-0.2.dist-info/WHEEL
