Metadata-Version: 2.0
Name: channelpy
Version: 0.2
Summary: Go Inspired Channels
Home-page: https://github.com/waltermoreira/channelpy
Author: Walter Moreira
Author-email: walter@waltermoreira.net
License: MIT
Keywords: channels distributed queues
Platform: UNKNOWN
Classifier: Development Status :: 3 - Alpha
Classifier: Intended Audience :: Developers
Classifier: License :: OSI Approved :: MIT License
Classifier: Programming Language :: Python :: 2
Classifier: Programming Language :: Python :: 2.7
Classifier: Programming Language :: Python :: 3
Classifier: Programming Language :: Python :: 3.4
Requires-Dist: rabbitpy
Requires-Dist: pytest
Requires-Dist: six
Requires-Dist: PyYAML
